githubchat_mcp_server/.env
githubchat_mcp_server/__init__.py
githubchat_mcp_server/__main__.py
githubchat_mcp_server-0.2.2.dist-info/METADATA
githubchat_mcp_server-0.2.2.dist-info/WHEEL
githubchat_mcp_server-0.2.2.dist-info/entry_points.txt
githubchat_mcp_server-0.2.2.dist-info/top_level.txt
githubchat_mcp_server-0.2.2.dist-info/RECORD
