Metadata-Version: 2.4
Name: githubchat-mcp-server
Version: 0.2.2
Summary: Model Context Protocol (MCP) server for GitHub Chat
Author-email: "Bluera Inc." <info@bluera.ai>
License: Proprietary
Project-URL: Homepage, https://github.com/blueraai/githubchat-mcp
Project-URL: Repository, https://github.com/blueraai/githubchat-mcp.git
Classifier: Development Status :: 4 - Beta
Classifier: Intended Audience :: Developers
Classifier: License :: Other/Proprietary License
Classifier: Programming Language :: Python :: 3
Classifier: Programming Language :: Python :: 3.8
Classifier: Programming Language :: Python :: 3.9
Classifier: Programming Language :: Python :: 3.10
Classifier: Programming Language :: Python :: 3.11
Requires-Python: >=3.8
Requires-Dist: fastmcp>=2.0.0
Requires-Dist: requests>=2.31.0
Requires-Dist: python-dotenv>=1.0.0
